README.md
setup.py
bjoern_cli.egg-info/PKG-INFO
bjoern_cli.egg-info/SOURCES.txt
bjoern_cli.egg-info/dependency_links.txt
bjoern_cli.egg-info/entry_points.txt
bjoern_cli.egg-info/requires.txt
bjoern_cli.egg-info/top_level.txt
bjoerncli/__init__.py
bjoerncli/main.py