Metadata-Version: 2.1
Name: bjoern-cli
Version: 0.0.1
Summary: A convenient command line wrapper around bjoern web server
Home-page: https://github.com/Gufran/bjoern-cli
Author: Mohammad Gufran
License: MIT
Platform: UNKNOWN
Classifier: Development Status :: 4 - Beta
Classifier: License :: OSI Approved :: MIT License
Classifier: Environment :: Console
Classifier: Environment :: Web Environment
Classifier: Programming Language :: Python :: 2
Classifier: Programming Language :: Python :: 3
Classifier: Topic :: Internet :: WWW/HTTP :: WSGI :: Server
